{"paths":{"0":["skeleton/cards/h_fedora_atlas_symbols",7],"1":["textures/language/rule/pt_01",2],"2":["sounds/Free_Game_Reel_Start",8],"3":["textures/particle/ib_vfx_e_screen_02_08",2],"4":["sounds/UICoin_01",8],"5":["sounds/Spin_Button_Hover",8],"6":["textures/language/text/pt/banner",2],"7":["skeleton/cards/h_cash_atlas_symbols",7],"8":["skeleton/bigwin/bw",2],"9":["textures/language/rule/zh_02",2],"10":["textures/particle/hbfy_bl",10],"11":["sounds/Free_Game_Settlement_01",8],"12":["textures/language/text/en/banner",2],"13":["textures/bg/text34",2],"14":["sounds/Multiple_Collect",8],"15":["sounds/Symbol_Drop_01",8],"16":["skeleton/bg/wild_scat3",2],"17":["textures/cards/en/card",2],"18":["skeleton/bg/bg2",2],"19":["skeleton/bg/bg3",2],"20":["sounds/Multiple_Move",8],"21":["skeleton/cards/symbols",2],"22":["sounds/TotalWin_01",8],"23":["textures/language/text/zh/banner",2],"24":["skeleton/bg/btn",7],"25":["skeleton/bg/ui_car",2],"26":["textures/particle/bl_particles_04",2],"27":["skeleton/bg/bg",6],"28":["textures/language/paytable/pt_01",2],"29":["textures/language/rule/pt_03",2],"30":["sounds/OneMore_Trigger",8],"31":["sounds/UICoin_02",8],"32":["skeleton/bigwin/bw",6],"33":["skeleton/cards/h_whiskey_atlas_symbols",7],"34":["textures/language/paytable/en_04",2],"35":["skeleton/bg/sd",7],"36":["skeleton/cards/h_knuckle_atlas_symbols",7],"37":["sounds/Currency_Button",8],"38":["textures/language/rule/pt_02",2],"39":["textures/particle/hbfy_main",10],"40":["skeleton/bg/wild_scat",2],"41":["textures/bg/ib_vfx_f_screen_01_12",2],"42":["textures/language/rule/en_01",2],"43":["skeleton/cards/en/s_scatter_atlas_specials",7],"44":["textures/cards/cardFrame1",2],"45":["sounds/Prize_All_Stop",8],"46":["textures/particle/bl_particles_03",2],"47":["sounds/Thunder_04",8],"48":["textures/language/loading/zh/splash",2],"49":["textures/language/loading/pt/splash",2],"50":["textures/language/paytable/en_02",2],"51":["skeleton/cards/h_rose_atlas_symbols",7],"52":["textures/bg/bw_vfx_a_normal_01",2],"53":["textures/bg/bg2",2],"54":["skeleton/bg/freegame2",2],"55":["sounds/Treasures_01",8],"56":["textures/language/paytable/pt_02",2],"57":["skeleton/bg/ib",2],"58":["textures/font/font4",2],"59":["textures/cards/cardFrame",2],"60":["skeleton/cards/l_a_atlas_symbols",7],"61":["textures/particle/rain_particle_bg",2],"62":["textures/bg/text46",2],"63":["skeleton/bg/wh",7],"64":["textures/bg/bar",2],"65":["skeleton/cards/l_k_atlas_symbols",7],"66":["skeleton/bg/wild_scat",7],"67":["textures/language/paytable/pt_03",2],"68":["textures/language/rule/zh_04",2],"69":["textures/bg/bg1",2],"70":["textures/language/paytable/zh_04",2],"71":["skeleton/bg/ib",6],"72":["textures/language/paytable/zh_01",2],"73":["skeleton/cards/zh/s_scatter_atlas_specials",7],"74":["textures/particle/ib_vfx_e_screen_03_08",2],"75":["sounds/Free_Game_Reward",8],"76":["sounds/OneMore_Wait",8],"77":["textures/language/rule/en_03",2],"78":["skeleton/bg/freegame",6],"79":["textures/language/rule/pt_04",2],"80":["textures/font/font1",2],"81":["sounds/TotalWin_02",8],"82":["skeleton/cards/zh/s_wild_atlas_specials",7],"83":["sounds/Reel_Quick_01",8],"84":["sounds/Wild_Multiple_End",8],"85":["sounds/Thunder_02",8],"86":["sounds/Wild_Symbol_01",8],"87":["skeleton/bg/freegame",7],"88":["textures/language/paytable/zh_02",2],"89":["textures/cards/zh/card",2],"90":["skeleton/bigwin/bw",2],"91":["textures/language/rule/en_04",2],"92":["skeleton/bg/wh",2],"93":["skeleton/bg/mult",7],"94":["skeleton/bg/freegame",2],"95":["sounds/Reel_Spin",8],"96":["skeleton/bg/btn",6],"97":["skeleton/cards/l_j_atlas_symbols",7],"98":["textures/language/rule/zh_03",2],"99":["sounds/Wild_Multiple",8],"100":["skeleton/bg/wild_scat",2],"101":["textures/particle/ib_vfx_e_screen_01_08",2],"102":["sounds/Click_Element_View",8],"103":["skeleton/bg/mult",2],"104":["skeleton/bg/freegame",2],"105":["textures/bg/text52",2],"106":["sounds/FreeGame_Back_Music",8],"107":["skeleton/bigwin/bw4",2],"108":["textures/particle/hbfy_bw",10],"109":["sounds/Remove_01",8],"110":["skeleton/bg/sd",2],"111":["skeleton/cards/h_boss_atlas_symbols",7],"112":["sounds/Reel_Quick_03",8],"113":["textures/language/text/zh/over",2],"114":["textures/font/font2",2],"115":["sounds/UICoin_03",8],"116":["skeleton/bg/sd2",2],"117":["textures/bg/carMask",2],"118":["sounds/Thunder_03",8],"119":["textures/language/paytable/en_03",2],"120":["textures/particle/bl_particles_01",2],"121":["skeleton/bg/wild_scat2",2],"122":["textures/particle/hbfy_ib",10],"123":["sounds/Free_Game_Settlement_02",8],"124":["textures/bg/bw_vfx_a_normal_02",2],"125":["textures/bg/blurryUrl",2],"126":["skeleton/bigwin/bw3",2],"127":["sounds/Click_Reel_Stop1",8],"128":["skeleton/cards/en/s_wild_atlas_specials",7],"129":["sounds/FreeGame_Button",8],"130":["sounds/Reel_Stop11",8],"131":["textures/font/winFont",2],"132":["skeleton/bigwin/bw2",2],"133":["sounds/Free_Game_Tip",8],"134":["textures/extra/pure",2],"135":["sounds/Reel_Quick_01_End",8],"136":["skeleton/bg/bg",2],"137":["sounds/Free_Game_Start",8],"138":["textures/language/paytable/zh_03",2],"139":["skeleton/bg/wh",6],"140":["sounds/UICoin_02_Stop",8],"141":["textures/bg/bw_vfx_b_normal_02",2],"142":["skeleton/bg/wild_scat",6],"143":["textures/bg/bw_vfx_n_add",2],"144":["textures/particle/bw_vfx_e_normal",2],"145":["sounds/Game_Back_Music",8],"146":["textures/font/font3",2],"147":["textures/language/text/pt/over",2],"148":["sounds/Reel_Quick_02",8],"149":["skeleton/bg/btn",2],"150":["skeleton/bigwin/bw",7],"151":["textures/slotMachine/ctrBtn",2],"152":["textures/font/freeCount",2],"153":["sounds/Game_Back_Music_02",8],"154":["textures/particle/bl_particles_02",2],"155":["skeleton/bg/bg",7],"156":["sounds/Symbol_Drop_02",8],"157":["textures/language/paytable/pt_04",2],"158":["sounds/Wild",8],"159":["sounds/Spin_Button_Sound",8],"160":["skeleton/bg/mult",6],"161":["sounds/Prize_All",8],"162":["textures/bg/payout",2],"163":["skeleton/bg/bg",2],"164":["skeleton/bg/ib",7],"165":["sounds/Car_01",8],"166":["textures/language/rule/zh_01",2],"167":["skeleton/bg/ui_car",7],"168":["textures/language/loading/en/splash",2],"169":["skeleton/bg/sd",6],"170":["skeleton/cards/l_10_atlas_symbols",7],"171":["sounds/Car_02",8],"172":["skeleton/cards/en/specials",2],"173":["skeleton/cards/l_q_atlas_symbols",7],"174":["sounds/Thunder_01",8],"175":["textures/language/paytable/en_01",2],"176":["textures/font/mul",2],"177":["skeleton/bg/freegame2",2],"178":["sounds/Ring",8],"179":["skeleton/cards/zh/specials",2],"180":["sounds/Appear_Wheel",8],"181":["textures/bg/bw_vfx_a_normal_03",2],"182":["skeleton/bg/wh2",2],"183":["textures/language/rule/en_02",2],"184":["animations/rain",2],"185":["textures/language/text/en/over",2],"186":["textures/language/rule/zh_04",5,1],"187":["skeleton/bg/wild_scat",5,1],"188":["skeleton/bg/ib",5,1],"189":["skeleton/bigwin/bw3",5,1],"190":["textures/language/text/zh/banner",1],"191":["configs/data/111013301/data/tpls/DataSlotBuyFree",3],"192":["textures/language/rule/pt_02",5,1],"193":["textures/bg/bw_vfx_a_normal_03",5,1],"194":["skeleton/cards/en/specials",5,1],"195":["textures/language/rule/en_03",5,1],"196":["skeleton/bg/bg",5,1],"197":["textures/font/freeCount",1],"198":["skeleton/cards/en/s_wild_atlas_specials",6],"199":["configs/language/ko",3],"200":["animations/scoreWrap",0],"201":["skeleton/bg/wild_scat",5,1],"202":["configs/banner/banner",3],"203":["textures/extra/pure",5,1],"204":["skeleton/bg/ui_car",5,1],"205":["skeleton/cards/h_fedora_atlas_symbols",6],"206":["textures/bg/ib_vfx_f_screen_01_12",5,1],"207":["textures/language/text/zh/over",1],"208":["configs/data/111013301/data/tpls/DataSlotLanguage",3],"209":["textures/language/rule/zh_03",5,1],"210":["skeleton/cards/l_a_atlas_symbols",6],"211":["skeleton/bg/sd",5,1],"212":["configs/data/111013301/data/tpls/DataElement",3],"213":["configs/layout/layout",3],"214":["configs/data/111013301/data/tpls/DataSlotRollerMode",3],"215":["configs/slotMachine/sideLineSetter",3],"216":["textures/particle/ib_vfx_e_screen_03_08",5,1],"217":["textures/bg/text52",1],"218":["skeleton/bg/btn",5,1],"219":["textures/cards/zh/card",1],"220":["skeleton/bg/wild_scat3",5,1],"221":["skeleton/bg/freegame2",5,1],"222":["skeleton/bg/freegame",5,1],"223":["skeleton/cards/h_rose_atlas_symbols",6],"224":["configs/data/111013301/data/tpls/DataDataSlotElementReward",3],"225":["wave",11],"226":["textures/font/font3",5,1],"227":["textures/cards/en/card",1],"228":["textures/language/paytable/en_03",5,1],"229":["skeleton/cards/l_k_atlas_symbols",6],"230":["configs/data/111013301/data/tpls/DataGame",3],"231":["animations/rain",0],"232":["textures/language/paytable/pt_02",5,1],"233":["skeleton/cards/zh/specials",5,1],"234":["textures/bg/bar",1],"235":["configs/menu/menu",3],"236":["skeleton/cards/h_cash_atlas_symbols",6],"237":["skeleton/bg/bg2",5,1],"238":["skeleton/cards/en/s_scatter_atlas_specials",6],"239":["textures/cards/cardFrame1",1],"240":["animations/accTip",0],"241":["skeleton/bg/freegame2",5,1],"242":["textures/font/winFont",1],"243":["skeleton/bigwin/bw4",5,1],"244":["textures/particle/rain_particle_bg",5,1],"245":["skeleton/bigwin/bw",5,1],"246":["skeleton/cards/l_10_atlas_symbols",6],"247":["configs/language/ja",3],"248":["configs/winAnimations/winAnimation",3],"249":["textures/font/font3",9],"250":["animations/combMul",0],"251":["textures/language/rule/en_04",5,1],"252":["textures/particle/ib_vfx_e_screen_01_08",5,1],"253":["configs/sound/sound",3],"254":["textures/language/rule/zh_01",5,1],"255":["configs/gameControl/gameControl",3],"256":["textures/bg/bg2",1],"257":["skeleton/bg/freegame",5,1],"258":["skeleton/bg/ui_car",6],"259":["textures/particle/bw_vfx_e_normal",1],"260":["skeleton/cards/zh/s_scatter_atlas_specials",6],"261":["textures/language/paytable/en_02",5,1],"262":["skeleton/cards/h_whiskey_atlas_symbols",6],"263":["configs/data/111013301/data/tpls/DataGameFreeLines",3],"264":["textures/language/loading/pt/splash",5,1],"265":["configs/data/111013301/data/tpls/DataSlotRandomGrid",3],"266":["prefabs/gameBg/scenePrefab",4],"267":["configs/result",3],"268":["configs/rule/rule",3],"269":["textures/language/text/en/banner",1],"270":["textures/language/loading/en/splash",5,1],"271":["textures/bg/text34",1],"272":["configs/data/111013301/data/tpls/DataRoller",3],"273":["textures/language/paytable/pt_04",5,1],"274":["textures/language/paytable/en_01",5,1],"275":["textures/font/font4",9],"276":["textures/language/paytable/zh_01",5,1],"277":["textures/font/font1",1],"278":["textures/font/font2",5,1],"279":["skeleton/bigwin/bw",5,1],"280":["textures/particle/bl_particles_01",5,1],"281":["textures/particle/ib_vfx_e_screen_02_08",5,1],"282":["textures/bg/bg1",1],"283":["textures/language/text/pt/over",1],"284":["skeleton/cards/l_q_atlas_symbols",6],"285":["animations/cigar",0],"286":["configs/data/111013301/data/tpls/DataFreeRoller",3],"287":["configs/language/th",3],"288":["textures/font/font4",5,1],"289":["textures/bg/payout",1],"290":["animations/btnHover",0],"291":["textures/cards/cardFrame",1],"292":["skeleton/cards/zh/s_wild_atlas_specials",6],"293":["textures/language/paytable/zh_04",5,1],"294":["textures/language/paytable/pt_03",5,1],"295":["configs/main",3],"296":["textures/particle/bl_particles_04",5,1],"297":["skeleton/bg/bg3",5,1],"298":["textures/language/loading/zh/splash",5,1],"299":["configs/data/111013301/data/tpls/DataPayLine",3],"300":["skeleton/bg/bg",5,1],"301":["textures/bg/carMask",5,1],"302":["textures/language/rule/en_02",5,1],"303":["skeleton/bg/mult",5,1],"304":["textures/language/rule/en_01",5,1],"305":["textures/language/paytable/en_04",5,1],"306":["wave",12],"307":["textures/language/text/en/over",1],"308":["configs/compensateTabel/compensateTable",3],"309":["textures/bg/bw_vfx_b_normal_02",5,1],"310":["animations/carMask",0],"311":["configs/slotMachine/slotMachine",3],"312":["configs/data/111013301/data/tpls/DataFreeLines",3],"313":["animations/popfx",0],"314":["skeleton/bg/wh2",5,1],"315":["textures/particle/bl_particles_02",5,1],"316":["textures/language/rule/pt_04",5,1],"317":["configs/language/en",3],"318":["animations/freeOver",0],"319":["animations/winTip",0],"320":["configs/slotMachine/spinElementResConfig",3],"321":["textures/font/mul",1],"322":["animations/freePop",0],"323":["prefabs/slotMachine/rollerPrefab",4],"324":["animations/bigTxt",0],"325":["animations/cloud",0],"326":["skeleton/bigwin/bw2",5,1],"327":["configs/data/111013301/data/tpls/DataSlotRoller",3],"328":["textures/language/paytable/zh_03",5,1],"329":["skeleton/bg/wild_scat2",5,1],"330":["configs/slotMachine/elementPayConfig",3],"331":["textures/slotMachine/ctrBtn",1],"332":["skeleton/cards/h_boss_atlas_symbols",6],"333":["configs/language/zh",3],"334":["configs/data/111013301/data/tpls/Constant",3],"335":["animations/wildChange",0],"336":["textures/language/text/pt/banner",1],"337":["textures/language/rule/pt_03",5,1],"338":["textures/bg/bw_vfx_n_add",5,1],"339":["textures/font/font2",9],"340":["animations/wildChange1",0],"341":["animations/sctWinTip",0],"342":["configs/data/111013301/data/tpls/DataSlotDoubleCoin",3],"343":["configs/gm/gmCmd",3],"344":["main",4],"345":["skeleton/cards/symbols",5,1],"346":["skeleton/bg/wh",5,1],"347":["textures/language/paytable/pt_01",5,1],"348":["textures/language/rule/pt_01",5,1],"349":["skeleton/cards/l_j_atlas_symbols",6],"350":["textures/bg/blurryUrl",5,1],"351":["textures/bg/bw_vfx_a_normal_02",5,1],"352":["textures/bg/bw_vfx_a_normal_01",5,1],"353":["textures/language/rule/zh_02",5,1],"354":["textures/bg/text46",1],"355":["textures/language/paytable/zh_02",5,1],"356":["skeleton/cards/h_knuckle_atlas_symbols",6],"357":["textures/particle/bl_particles_03",5,1],"358":["animations/rain",1],"359":["skeleton/bg/sd2",5,1]},"types":["cc.AnimationClip","cc.SpriteAtlas","cc.Texture2D","cc.JsonAsset","cc.Prefab","cc.SpriteFrame","sp.SkeletonData","cc.Asset","cc.AudioClip","cc.BitmapFont","cc.ParticleAsset","cc.EffectAsset","cc.Material"],"uuids":["00IwdrT8lKLaF9qR3Op6WD","00L4l1xvxEY793BU7PXdyh","00uDCBeBdDk7LmR/zsHI/o","01DEdEWApHg6NvhLAR3ZK0","021mWQX3NGiLlRkrFnLy1i","04A3R7d4NLN5TSc7vbzm2u","06Ad7S4CxCp7jbjYiJV8Zt","08Y6SYUwlEeYos6xSYUAj9","0bTBbI6XNLp72Me8BHatDw","0bTbTdL6pLrrP75Zu+Y6Ys","0cW9CbNcBEtZ5tAfRhPiAS","0dk/cRHspBfq+cXQgol0h1","0fT80NUpRKjqMrgVw/e+RG","11xG3JTLVElY82iMUm4o0A","13aIm7wGpCY4G3fL47ivsG","148Wx7HIxELLaqrqjEplr0","15eR3vAfFOeLxV44dJiwrz","16kd5o8vNFcIQGWEkiV3+B","179Y9a/YpB9qJxA2duO4QW","18Xx3Yh+1Ek6oxCZqBSOuh","18u+sZh2lMEJDXBaBDPYBf","19TLygeNFKO7Pw+WXxxHob","1bGgPWVYJM9JsftiaWDLSA","1dNCUgOSFMRKWDcXcFP/Tw","1dX3+S2jRDXLb+woxwp8VD","1dY47p6BRGY53QDNbM7z3B","1eyA7fNyFOT6TDqbBTXP9A","20dEJbX1BB5o+RbRd/QAx8","21IRm01kpBzqP3mIh3oftY","21hMmhDwRPR4Dlj9c/kT0J","25H5Ak3KJJE5jghhzTpRHQ","25tz36uNRKN5i4/WWvkj0z","26TXmsKChAQ5DFOjhxdf7v","27ISqR62pNdaCe7Kq47hoo","2abt0o3rlBXJdnCR+HJTaa","2c9cOrFvFCjoWflz5kQ1Xu","2dRTeQvqxOq4szgY1ABWyi","2eVjetoxtDfJ7t7F3PkaRG","2fKRzeuE5BYoDn3bOLH3Nq","30G7KShw1Ed5jgyi445KfI","32zz0s5xpHgoPyhzl5jr6/","33yBRSz1pF5pvpG/JhSB6g","34beFvNzVGGZkNIshUclTk","34rkNejkdJOYgLyWokPMih","34+VFLQsdP64xyl4VaPVim","367ezqbYRCzYvCYJrxhYqU","38QGJf7zBOV5AODv663dYB","3alpq/Zc1GtZTXHMTr30Jq","3dp+UMtC9DFpRreYMw5Uio","3eOOlT66VDIIT2me3Rn7Wh","41EPUiZURNVZ5xwQj6lBC0","41lcdQmwdHaJmByelU++vu","453K7RLV1C4Ix+Bvssll0c","47UlyeD9JJ/rL52OHDtQUc","47rRhflkpCuqyGIM8YeUpO","4aMLJzmOZAMZ0mWZHcndYA","4cxwrwKhtMUqkHL2yDhUja","4c5tF6LTBPmby4pE+yvPd9","4dzyQ7y39OCLYreVMg7VQ4","4dz2eLIfVAz4cxxUuVo6Nx","50IeDFdrlN8KOWYdVa24YN","51aszPX91LYajRVgFnK2GQ","55VmzbL3BARbUJofxLpZwP","56flckrw1EgrYvkVJS16JQ","56zNVzqChB3YyveWdVZwm5","57LIYiY89E44Hfwpcqej0p","5955fUEW5AyLANZBWErNhb","5aAN1xlrBIIK+Hz4k3njWF","5a7qag+xVEd4LunNyU1Cba","5bDsbEE7VLio7P6kmgXlQc","5cjfWunmNKCISVl+mHAE3W","617THZwDhEvbWKlK0efP90","62pKhNEodAJofGtkKkfPzQ","63iTUgrOxCc7Oo4HTk/Ead","64slLX96xCq4HD1Kn36Ldp","65mBHuHfhAxpfDv8tt982X","66JD+7vqxGCItsVC/gLs2j","6625OriXtM658SkD4EY3fG","674CNmphJNJKskDxwTgAdc","68VK4z/ilNE7Ezcxe0r3FB","6cYqhq6alIOrLjro5XwSo0","70n7XjQERMAIyBFz8XIf2L","70uxm3XLRIiKyNO8bnQyLx","73eZYHLntGqr5KMsLSZokt","74fl0pW2hFRL5zrY7Br28A","75mFcCMhpIBJ1/ugVo8If0","77P3EtCNNAPpM90tuY9f2a","79oXYdbglI/6Qsj7g0lJWS","7aDecuEWZA+5y6v2I7QF+l","7b+n66CaJH3KMYwE5Tpzoj","7eLM/5Ed1OTb4P2RZFFVdM","7fnluYoJpALZ/LrVqJrAvW","828gqL645EKJ8NABMvmi6F","847KZdKoxIQ4oSNswpgAX7","868aOUXYBDXZy3xIHXGyna","89hCw3ZeBLt7R+4MsOx6gI","8aoLKdCS5CuLKF57IfoyWJ","8btqDvOrpNarzmXtjAQscA","8dn/eIyT9MKa/62xcOBWdN","8dvjKKX0xIQLKbQ756NUgb","90LDV3GStHzpVvMxeq9tKH","90ZPTU4YxFHq/YHNGJRfrG","90maO1tVxFEoHZCFs+jNzc","909fD1+k5BjonbEAxr8aq+","92CPaMCRdBbo7IgUVJ1tCe","92LCnqN5pH+o1VTxWCwj+X","96L/rXbMxMBY4ci4Ax7vPa","96ZB4SAm9BbKz51JCqoPiJ","97Ux01DqRF5LLMXhv2m+kQ","99Fp4xnE5GprJZJA5lR9NG","9cDPak8oRMgpjy2rYeVqXX","9cJ7znrAhEML3QRvf53wZ/","9cTBRPF2lM65KwTR4HNpM+","9cbyki50FA3oY+VP8WNgv9","a0dX9+IYRPjIn8KfGgTNO/","a2j1EniiVByrvyxbfdMFMg","a5CzIUc7FCUpGrx78GSm0Q","a58Xvv8WRM5bKuwYJhkxuC","a6+Y9v4yxHd6H5CLbuxa/6","abuLyxaHBHMqrwvcPKxH4M","acgCsY62hEOrkwVGyH9v0H","acqkv+p/FPSYxOeRrFwa0M","adSUCyF/BLBJlApdSRNz0U","b0gE4VqUlOVIO//PT6LRyQ","b03/6kCrxJG57yIS5qCAFx","b20fDpPu9GJaekLRtqyCqI","b24DS6sG9KAZNxrHrM8a/w","b8y7AeZQlEnbvKjfxmWTZu","b9L1EXZqlHkLw6V/wapVCP","b9RRWC41dP7Yujb19yk+jd","b9YjOlJ21KmbdT2vy5EA52","baK71zMb5A/qkG516dvVz7","ba9fkwprRP8Yuoj6niXE/t","bcgwW3t+dEZIX6FT3gnn3y","bd4/fCXe9I3rGk3wpBn13Q","bfNoQ0BWdCcrSnSUOG/j/+","c2ebgH16BPa5RrjJ0Oahx4","c3ONuLdqZKR4yyUw4FVWfp","c3VnRfCsBIXqwTwn/6oYsn","c4nrzmephLsa/0C00XQ8Og","c5jdT7VL5G0p7cnc/o/jeG","c6WWrTm0JB5bim1irLcvbx","c66Hd0oNBFRqEYsu82cb3t","c6/5PsPc1MZp9aIN1/Pq9d","c8cdcRyxxI4rMesjwZg3BW","c8qF7l5JZNbZeJ7XRmKWb8","c9K23VyH9L/rpUYtlayiYC","c9cCYlhuBIJIobQzJjJ5yO","cbexVDBARC25GpC9+DJ9ib","cb8iUPfbFN/6tDJV/uQaZd","ceewX0kH9KkJLgMIXtqwo7","cf9/J6MYlHbYcDev24AqzI","d0jez+QuFK1apdqWJD8yOh","d2LL2bYcFC0Io/5O3qSPac","d3AJKi7rBE8b9Ryo436uAd","d5JjXuAZVNYJYM2KMvutO5","d5dbWm0aJIkYUv6m13BVo1","d9HSM0fC5A6YOpPGLhapse","d9aq1x4QJFr4eZIxuGnlso","d9e8P3OHxJQ73n+BvIlTsD","dbfbszRzRP8ILnDw05GEFj","de2K+tR/tNhIQghpAdQYl3","e0Wp6k+TVLHJwv2pAWawGb","e2f5+CE7tJ+ozfNGoHFEO7","e3JQuzLRdGM4bDyKMSI77u","e5atBnaS1PLo8ZsgSksAmy","e5lODq63VOrLeMe7VCroR8","e7D/tULAZNXoVsFKaRwzLe","e8u24agelPpbYMk97N1DVS","e9kLkRc1lOVr8tmiPigwEx","eaiSBaDnpIsJ4JQVqblzL0","eakJfv7o9F27FfcEh1DGp5","ebefa6fqhPca0+D9IKJDDq","efNInrQMVGlqsBdklQ61AG","f0A0f+B5pMtbvQEPA+0wDR","f0HFHdE1RLXrr8fKlQA9zU","f28wQ/fitC8peRxi9HsGqB","f3jnWYO7JOkJQDBoknFyCs","f3xN7fUV5PuoJFs2vgKw77","f5HcZF0MtLuZ2Sc0zXScev","f6R2bs/m9L2phT9NAlNogp","f7v0hEzQFINaY7pJEJcIau","f8CnfEm/BGXalZhf1qUFnj","fbilaLm5VJjZBbkiAO5S7x","fcYFuqrvlOi6K7D3dAMIji","ffjTeuJrBBLK2mHPwLNvSs","0099Rrfa5IqY4d/z9yaFZO","03Rtk4pw9JdqzdCUQRHiU8","04CkyJKu5MiIVeuV8WPGsF","04u21MMlpB453CVsWpVIlu","07Tby8DzRA8qMsWvATYsXs","08Rk6RWYNNTqJhESDUn+pl","0a8+QsPO5Ml7zfFCnyvwof","0cfZNCsKpKV5AdLRajNRfx","0c5XDPIQdAVYcIxdBpZ9Y+","0d24mw7AZO96wHNKAN0pvP","0eJoPbGTRO1rZ8RhL3G5VC","10ZfCA1BtAfp4WNSa6RAk0","1074skfJlKkJl9RdlKE2td","11HZ7Z7RhHJqMOxj8AvfYr","11Tb+Vw2tBXpv/Czy2TYYU","11ZJee3vJFnLYWnFbmIM5T","13geRSBBdOT609GOZyl0W3","14gdgwjFpN9Jk0dgsHC9mS","16kDX0XjVBJqEHcH3lT0mX","17nkWM1P1DJ74mU50xJpFK","20HLb3ycFIjK1FVrkY1tSf","20gZPsIiFH95AvQRbBoDwg","21abcCvEdPnpGbWLc2pDlE","21xYN7OZFOsK+ywpu9eUzc","237n2Bp8BA15koUeWtt+5T","24NPVcgIJKCZWQFyHKU4j4","26pvG6G+tKEK7lC0+mdFUG","28dns98zVFYaaqcxtyptYx","28mxsCozlE2IfZzszR3OEp","281wkuYP5Kl4vOWObiaHBp","2dheSJzIhFFIwQiU474Jhx","2e21w95HVOQbg3o73gRRoW","30yTjm+1hJuY+xKaziQfMH","31xJ0db0RAHLW2XQObhX9s","31zeyW2yBGMbmdDQfQwQLC","31+PE7Dz9Ky5+si0kjE7Cf","33Jp+5sZVNtILOfndX04Oj","34deV09l5HCYArC2HoG6oM","35FL66byNJe5n9hfTVox+r","3bybEhD2ZHaL9I00lizPua","3eQoAEaW1F3ZKKkkMWHxej","3e+OnC4itJUKBOejyF1ash","40Vue97oFMC7eNNLaXRCUa","42QGgegWZHP4M9d5Jmks9H","42meaFTP1OqJuYInbMKGgT","43nXqLHK1PpbVl1zCa4KT2","434TDLiGhHn7waOaU1VnA8","44PCFeb+tNEI816mmKQLVB","45jD7igAlII4+dpZhTxYQ6","48u1pLhgtHiLW+LmBX8J0I","49aDAmTqFPeptTopAByetX","4astqDk1RL7oOrVa3KxAmi","4a7SNAESRAHK6ZeQm0m1f8","4ccj3WGoJI5qAeUSpFo218","4e+AWX/uZHZJbrgHShaa9Z","4fxKAndq5Ij4yh10jP/hdV","50TovG+iJBy5z68QM1tXwi","51BVIpggNP1b8uqRWy370l","51l3ORS9JBy7P6ABn9Pm23","51yPIir/pAkYPUGKwYIGvo","54G9cg/KtBWZxjybKLVcck","55eIBtkqlIF6AdgJ4yJBI1","55rfIIP4NFArNfxtxDA2eW","576P2D3BdAnKrK008LXuLD","58yS61PqRBj7znlRT3wsij","58y4qfZJRER4lxWOeuD2jV","5afV0Rm6BHtbl2L5eOjQgb","5b78ez4utKHJstl5ySw9zN","5cypZqxElE2KeXBNey6Gq2","5czXafgN9Fo4AyHIu+VuBi","5d+6DVZ89M9I1hG+ZbiXKJ","5fO3Yw3u5LJLCy8M9rOiDK","5femdJjzVP67kc2a/hluNo","66r8Bp3AFFv6ZfgC8SFUBZ","66r8W38QhAqa42lRWrLhxC","6fcCTJyEJILbnV/InWM+Z9","70KGZBTy9MvoUjtbV2I5iO","74T9YQYPtHHaaq2r5GNyLl","75FsitLUZNzZz5Sf2lzYrK","770Ks68CpCbakMGqD4+MhF","788n4HXBtKl5z6Vu2FzbvJ","789wYKYUVAo7RiX7AXZU/N","79/ALyF7xPgLZWhsFu10Hk","7aQXwL1nRD1Jx8eluq44YN","7bKabFVppOXrXVAwGIgWoe","7dKSy33HRO05WQuwvDPjBa","7fVQdYzBxBko+C1rlN0QVh","80qwBwtLJF5o/riGfdL+Hc","81PoHTTJ5Gj6eMr1ku1nRg","82WLmGugNAvqj2U+2hOOvZ","82WMOpkRVO7q6xoLtXLPSi","82hgqTUU1ClL+7AwB5GXGp","83XRUrzu9NhoNOftmcdB9j","87fm4TVf9CAoGH0Y5qcS+F","88snRtyQ9B6q4CXyQMN3Rw","89cgvbsyBKwZfaYe2YQG+N","896bwQQ7JP+ZljXWCnz2C1","897+CaUe9FfIKuzxbPDFOo","8cd3AssFFD8o9/m/5u/X38","8d99erWSRLorHJadr8LfKJ","91OyzDg9dAJaY//UKwU+dy","91wbT4RBxM5LjU7UNfOTWf","92UJG9dclKv7DY+TVN9YoI","92kTREoPVOP4jGFO6jusUQ","93wvIz2X5JmKTyZAdoaQz4","94CYaYIyFGapqLdmjVvXhP","96qDFyWQZJEb7VgKPP65r5","98AoAPvO9HY6rLQpCv1xsu","981GiY9ixC35bhpJtYl7Lq","9axOCTUURMiIDIbPdqV9c3","9bHYhexhBNaa0K2v+mpHOL","9bHqnLclZAAr1cTLvYChn4","9bLtBLu19Eub4kibXnoQB4","9bW5CBb69F4qlVdXwl0IV+","9bqsl2yfBHXZHe0NhqAfme","9cBrK5CexLG5SkDHTWm4eM","9fjxipTqpM+JDxyB23Liu2","a1xobVV2dCa4Gmx5gS1FwT","a210ehkbhNNZ+KbKn/ZM42","a7LiWLOkhEPq7d21uvK0Ml","aaB595JI9HrosxCSFvInop","afoptAR2lOsrwHJ0Nj5Q75","af8WV57sNIfYOnyc08a7ax","bbn+7qDV5O/JWMjinprG0g","bcdv+vrXlAPoh8f7udqwA/","besjTAG5JN55uUTygNKwYj","c0mQCiFYlN5LbyRLnWJsf7","c1MNvYtTtLlI54XR6Lns9O","c4lKSurjdN1pjRsoAR4Yo9","c56XY74L1CzY30as8COchd","c6Gw23eNZAMKEKSqSyoSIb","c6kv0zgsxDm7acP+tTOpvA","c7EJGX5q1P96zqaa2s9gxb","c7F31Bu85K7rzoX65Psqmn","c8gnYL7CtFQ7TLhEuEUFax","caXfYpcgRMEITtXPpj171b","cc1ZDVv5RLra/LNYHQ79L5","cdIuW+5KNMc6+VW3fUXvvU","ceri0/wYBLzZeT4afCEeZy","cfG+D9x+FK4qStYvtgALuQ","d0XIz34npNtKZH4AviH4kn","d4ulH0ObpPQ7F/Bl2NxCB5","d5D4w1IeRL+Jcmv4UmMY9f","d6n2UfZBBNU4BuQMTtxtp4","d7mzZ43V1CI72DIjdOLe/5","daIYDNTltITLkTEKbdXWw+","dayq5nhyROy4RGZ4Ic0Gva","dcWB4lfuJCO5/r/ALJIMWU","dcwsRBqnFMSb1R/9ldu49M","deQHDadlZNMI7L0SUiavdZ","e1+dWLtHRFh6HgotRYtbLT","e2Mw5jUV1CrrAgYWz4UVG3","e3OJXzSJ9BqajM79bY2nnc","e3cc5pN6dIgYiYsyGW+q+P","e4sdtwHfVG+K34s57sFc4k","e4taqfm5RJ77fRD+RiZVK2","e5E+laEvlDBptHQ0dECc0p","e673Xo4SNExIFbCVGoR5tn","e7IubL9VFBDo8tU0xJd3Y4","e7bZxPGrZHL64TBt/ozGmk","ea2jU/fspIsquUFd8JhIHm","ecmUpf9U5LQIpGLDphhB7G","ed+qSbJ5dKlIdtffhrhwVs","eeM0VKNTxCdKLCXsMShfvP","eevvaDGKtJE4cuMJ88uWel","efYKTebU1Lc7rmQJ121QXM","f0tJ/cECpAXqAo5HSGAKhI","f1tWU79zBN3oz6/z1BDodE","f2M2WkRERG6I1i59XM8GwE","f7iBUI//tEFoMy/0thZPPK","f77u2BGdZPEYwX64+PVH/R","f94ke4YtdC/6nXAI6F7Mz1","fbacsiQjhODIBoMfgtnDRo","fcuGVJwJlOLLMHr+0eZoEN","00g3//Dk9P4qwFtJHcxqIm","03PZXrEAlHrKAdY+2DD6hZ","058X6IkmFOIK606bIozQf9","06JJQmtqNHgpQ0paw/1oyd","07BqS/BW5P5oNpvWgieCn5","07XrPWZ/pDGrl6CRL0TcOO","0a0VJH6jZOe7Vj7Z3kOxk/","0bolTKdLRIAK2JHUlvq3bM","0b0ns+xohGxrD6ZyhfVyGL","0dc/lrG25B0pNQARNYi+2J","0eFHgG+1ZHepPuUT3nWHg+","0eQI33ei5BopAl9+ELH6Tq","10PYCTRtRBMpLuSzqQ7kbw","11Lo3jWoBCUIYeltHrtTPG","11ynfClqxC/bp8XK9o4fbT","13SXAXFhdBvamXUQ9EFeCE","15DNG4BpFEdq2s3QPQWWJB","16B9Hm+S9NwJjLIKukATHf","16kByRlo9NcKMN2xGWXtQO","166vwyQXpMX4wOUDpOnoWy","17TEu1SIRP7KSQA/cVbiDP","18XhKOWm9P2J7+dD9iaXOQ","1anS0u0F1LxbV190jj0RAJ","1b18YlVa5JnLhQ/J1Ip0up","1cA74EX51CYbGi8+MHYagN","1cZ7TLjytB2YYNMntUxybz","1c/PT5XWdC5bFQtq+Rvogu","1eiMVpEVlK3LF0zLfr+07N","1fSPieahVNm6oGmU83EVEG","1fVQQFTp9L6biSr/j9jBJL","1fWEcmzp1EGJikS1JAhXpG","215PcxRotDLrmTUbiPCgxL","22vPgFCy5BGaFZz4o5JB5f","25LjTc2rVPUbXHDimRoCCr","25Ykhyp8VCS58qgWL7890C","27SvqnqpxCAYU+UKHEovH6","27fHABKxRHQYxdDabc8S0q","278xMJo4NEppuPniXJfOvF","28rK/GRehO8JYmFZRGuqGk","281ExeovxIlKNLrBRdBwxG","29F+WcqyNPPbXQ6gCfD4sM","29STF+G6pJQbZQFH251dBs","2aQk44WNJEv4vPyFTSWw8t","2cNFowSZROladygQmyPo/O","2fVvdAm2ZM+p8Yn5SwcD9u","2fYwJ4AHVI8JKc9Fri5Mds","303AL1AaNKBZTIdgDMG1JY","309ASoKvFF6bS6K/soEClj","31NOa07M1LTLOTt5c/2IQB","31zmShcddERLI5RwJHWkpt","33Nf/nZbpK9r6Ep7k/qFFV","34TB7IZadI4L/ahpwv4KQf","35OoizE35BzJadzuMSyyTG","36YPjrFodHM6c6iXoFPo+g","36v2gR091KGYHHqPzR79kT","36zJDDZxBKGans5Oy35ApT","38KtbydHRPr6CetpPos/XX","38e+L3s05Kwbo53VD7Qz/T","3aHT3e019JdpXj3fN9/hO1","3a6ZeUxmJKKqabiOlC1vaa","3cgr1qzrhIUqmTC96d4Zm5","3c2F9z+edJFbfH8UwVlMMf","3dQMPusEdD373G8f1wPKsx","3fFpBgm1xPIpjesbDyE+7o","3fVfu7/TRGgbxSMYPPdsdZ","3foFkSiXdBNILjK/OayIga","4116mE/bpMU58ycncd36V8","43Sf/todFNw5KuosEd5ZEQ","44MyTo5gNAV62LtvW0wSS+","448d7SwqdGYLv1uityl6gb","49w44UzV9LvqfWF9GdNFlg","4bBHkzxERPUavrqfwwBjcz","4cc1YP37dFcaTIg7NzXWWP","4dI0Oxg11IopPfRFPvtrzd","4dt2REM0xGYrrgzDX5joQe","4edRodE0RBALT8QJE3BQih","4e0uiDehhPNL6zT899o6JZ","4fcPhphytFrrjNy58sd4rs","50gR1BIyNLmKGfCgtD+jGm","50pGxLN6VH74RFTljwGeb9","500uVh+kRIz7SRsxQn8UEA","515X1NmEhHvoDqToVH0+3I","516GxhGbxHrbdsmIAX3S9G","52gprwtI5JtZercn70HQtE","529TwcT+NGJq1RU1DcbOTh","53YUbQS3BHP6qUaVaYjhe7","54LaYVVURFl5M6AyWKJHld","54aI/aEQlAZ4qaDf1ozfge","55PVEfhpRMUKU88tJBU6nI","55gfJZhiJAmZM2cdmzMlUH","56bPX2AMBKAqFzzJV1Q+NN","57QP1OQV1BhJ+ObsntGmXs","57o9ZMUMFPpZLRfc99V17P","570Spn6aRPxJ2UGvRPACdb","575Flzq5VNObSsdMux5wbA","58NwXnoBJLOKA5oWQbqv8Z","58WRWDHWtDm5/aPcVcQNtp","5b+BMGJkRJW57p7eDV1nfu","5dhzsG4IRHVYhJPZnKiDJ3","5fEWsPmdlIYK1osFhQwPta","606VvGucxD/qYAq5ZXv7dC","622oh4euNGI6H8RsFZaq4A","63zyuJBNdNXJm9rPp5sYy2","64xsUWQPVGiY17RLR5QdS8","65dWfL3ttGGJDvazx+hJ27","656E6n5FlPxJnuIISztvef","67A/45qipOM6xP74Zn4DUY","67Eg1hahBItIwH+Iq0gRAo","68CJvt6rxCs4EFYdVFkfSN","6825s4i1RMoJ9iDY/Pb/QS","683i4RjyND/KMANtj3MZwT","69zJzXyEpN04UzwNFBAXSW","6ayBfoHc1PKp3a+b6NfVqg","6ay5HPj+tAhpIkeL8541H0","6a5e5G0oBBwIwgMoyrVFdN","6dURpbvf1E34pz7kebE7zM","6dnHuR2OlKNbaPTUfGYbwg","6d+Le2UlBDmJUdp9fBcJ27","6flKg5WjxLgarwNIRUY32m","6fqkqCxOJIApkEN5TSsPb1","70HSCXDOBE8662eDcYDP1M","70hVYJo01OK55A00Xa6Afa","71e/y2lYBDUodLMhAv6WRW","71hizPhwpMZK69jslkUsvF","72uxNf4N1I94pHVb6zsvNh","737cc7s1ZIQq+iF2NGJfT/","74AsbWmkJB+qGu9qUipimF","74CQJKmDdBlpKxv4g748C3","74HbBbS01GsZhe0Nvp7AbS","74kXSE2VxM2pVYDGpu17xf","75cAEvvCZD86mSlUwx+058","75qz0pOnVDGJjzq92FycUL","753BBLqQdJlYObovNn1bky","76UfvX+rVLi7z30vP32znB","77uUV2SzVKIbpUrzDkUVQM","78bcAqsldGdbuqQ+YO4SSw","78jlRR7kpBkJ/IYG6JF/R1","7a/QZLET9IDreTiBfRn2PD","7blvscvhZFZLjLthVZBsBA","7cMRt/rDlGKZ4JxLVkyQj1","7cQuSCBKpLF5n5hPvedbJB","7chy1bKcNNlL7v0ELWJrcZ","7dUkOebd9KhoRHDzP1deW2","7ePhxF8LVC/KfkwQGnzaCB","7escEFSCtDBpYY6lqfsLR1","80Li0A6ARA+aWgogrkh4mm","80MeyzfnhJNISbWt51fTLg","80poCNbUxA/q3ZxD4sj4Sk","80wGRzY09LJKktICQ+sap9","819IHqIGtPzJlPS4+kL7On","83Yf83A6pDqJOoKeDQuMn3","83lEK/QWVDebJItao9EZ2t","83sXFaMf1NDaP1OpVvWFWw","845w+vxdhN34BVYF0Z9lqn","859+zZslJJ8INkB7CPiT/t","86ZODbp0xJ1J5S4BEGpl0a","86tKD4xVZHOasz62KA+3J4","87FYdaQ+xJDYCX9AAJrXAd","87KLVdB1tB/JIOiPrLx4n2","88ok64RWFHoaHoaats/ygH","894b2qHN1LnJ/LZhxfp4BJ","8akeUC3/1KD7ZkKlX+e4nT","8ax9qxeKVCT76QDo3ghAmw","8a8vsYZRVNi4WhVzSvotU1","8bgaHurO5OAbFxX5uTio13","8cRzIXmbRHkoaUTPzn7efz","8df1dm9KhCO6FJic8AuwgE","8f2PBrgh5Gc5t9e7nTsl1i","90rv2aUT5Ab43jZ9Il/eYo","91G0/V3kdFzpKIKGzIfbPk","91mUWTDlVPF5DTLQLB18GL","92wMMbPmNMK5+oJfw6c9Gp","922NWktYZB94b8Fn7Ee4Yr","950+nIgGVFEIiQ/vX5HYZn","99TlehBEpPlLmXcNGI8Hlc","99pkupEMFF6bA5EhD8LhJR","9clBNUHOhJAY6PDcgxJsdi","9dkhlLJ0RPOJtItxr69OkS","9d9peHZXNOn6bDq6Bpey3f","9ebis0Mq9Nlpp3mjArLPUa","a0UuJls0lFrp6l+pO2EiDe","a2AGDSKK5An4A/VOmvOA6O","a2rvmDFYBDRK1Aq0MxQSfb","a29rdspFJPzab5F6eeuhsA","a3wJaPar1A6oxohcq2+5U1","a36gQBH3tEILkZwuQg6Fha","a5kA/DPP1BL6jN0wmOe+iX","a5qBw1XulOn4mJ7DW1u8oM","a5yN2TXUhID4jHb4130Bla","a58n4P7MdLY4gYIs6kVhWj","a6MMoQmvpNR4gNa6KFHs2A","a8QAmQlARLj6XZn2vHtQgY","a8eWAyn+9JlLWCnGF1gaJ0","a8uM8FHBlK95fl56Fedcm4","a9TXUbvQJMRb2PkXqbQQ6J","a9Te71DYROkJ9rQnrjnqY0","a9ZxEBbmlFdLPeRSxsXr0V","a9fRc8TcpFpbYjDBbppsXl","aaJrZuFgJO3I9jv6qJ9qn7","acihqfUr1IHrhDnYKztr/C","acvuAuppVOX5EijRORcD0c","aeDvynSj1P87MUp9TZcKnp","aeJDEE2jxGC7W7g20qbGG1","aeMUGrvq5Kd4qf7Fe+6OJM","aeTI1IXeBGpZh6b6Bvne2s","afwYxm5dlLkYIryjxmxkbh","b1C7mh6CBAyJ7SwYneqs2v","b2ApWYnDtIn7QOxjjM17vN","b3APubxxNC+Ki3vxrnwYOn","b3RtzYA+5EiJBpY05nWsdi","b4MbrWnclPp6r2erscoMz7","b4TD5JjyJEbpxtyNoKNU8v","b4caIJrH9FJJL/khNj0Q78","b5QaVL9ptHJocYcwCPyUP8","b6PLXoaFBAqLaFTYptvBfH","b6qSs6GgRCfJjc5BSDmpCe","ba7mciAzxA04Q5GY8sYgEf","bbkGTzoLpAPKiaNUCaoqRh","bctqiDhrpAj7AytOPOASCq","bdV9jQPLVJxIufnCXECWhE","behEgMzJVI3KDckJXs5fqT","be1mLx+9FIHqOj/P26S5la","bfE0oPvRJPYbt4vlPHU6Em","c1OC2g1BBDbargiifIV7Je","c1fnIsxqFKLq8p6U5jqAT2","c2QyZlLcBDgoidYAFMRAgV","c2ZQ4DX1JOb4z7Na2rSP+7","c2fab0P8dCbY17NGQkbOLV","c4wEOn2i9EmrKVrv2Ht+nc","c7RNsGvd9K1rR9Jv1d05KJ","cc7OrRG+FBsLjBkoxLJFzk","ceQ+DJ0UxCh7cmLS+QJG3U","d0kRteY25PPL2lMALGeYkU","d1i0NzoyBOn6+AzTBprRPR","d2xtKINhRI3bA8rXNJ9bCJ","d3YWDW55ZOhYgXoYRbjOPJ","d4x433hshJKpqgQSj90iQ7","d5/fXcJJBLh6XigjSm8XHo","d6aqi46nJAIZtuMj9nK9V7","d8DmgHhzhHGaii/0ax6FXR","dazae25mBLgLBktP8KPnAs","dcCxA48nxC67dhn1Em1n3X","dcPUkOo01FcInLXphyIN9T","ddNG6S2A1EDJbzcHXPxOjx","deRF/RfeFOK5OqDJDj3j2s","degCmpkHpAzqIOutPWm5lu","dekAAGpXxKc6PyxruGn1o4","dfa5IQRIxOj58ShNLm8PBb","dft9zfngNBE7KSZbpFzGbA","e13D+rLU1Hia4+leueK+U2","e2peGS1lFDbqEizohDefjV","e2rDmPW3RGAYTPs4w6KZO1","e3qGTo6zZHc7+0xTcniuJQ","e4cBdIrZdD1q1bmKvAd3O5","e40AlNfsREI7NErYqF80F8","e6hMjphixBCYEpM3bs2CWy","e7/Jm508tF+a4btQtzO1ES","e911oUSXhO4rxsdqF1BVeb","eaTDs2FyhBg6QQwpdlVIKB","ebEhNxI1xGKbvMhEsL8Zh0","ecpdLyjvZBwrvm+cedCcQy","ec8rOMFoNM0qwyUJbfQuRA","edH7vD3+tNR55Ihnw06UV9","edUt2/EyBBYLPVYq0h8+D5","ednmSZyJ5F4YYreGAVZ4hA","f0xBf4L/1GbqhuA98anlUr","f1D4dPeolK1a+wIjLG7TUb","f2FsdTJ5JD8bt7z51E3bc6","f2wcApK0xFzp5IaRnlFL1N","f5XPjuHqpFlZGd/D6Q5xWg","f5hC/syEVM+Jmaw1Q3JORU","f6cjpMxVBGmqie6YQ7oAi8","f6eCMRMU5GcaupmOqek1OM","f8J/DqvWZF6oYQvDaF6u7i","f8eXbcxVxOKZYA1pC65ZpR","f9DOOU4fVM9qOy8RZDqt5s","f9WBrlwQtDUay647My+YqY","f9uUfcjGxEdLHGjSm7jm86","faYIUSh6RHh6eJoOGw3GFQ","fbcJz9oeZP1aTtBkNeX8K1","fdimRJ4BlJOaq1O/3CIjQz","fd8H1XpThK572vWwN7gR+M","feMOpukbBMo6o4pMz3aNnV","ffguL+x75Ai52mFOf4XMns"],"scenes":{},"redirect":[497,0,620,0],"deps":["internal"],"packs":{"0d923bddd":[0,1,360,2,186,3,4,361,187,5,188,189,362,6,363,364,190,365,191,7,366,192,8,9,367,368,10,193,194,369,11,195,370,196,371,12,372,197,198,199,373,200,201,13,374,375,14,202,203,15,376,16,377,378,204,17,379,380,205,18,381,19,20,21,382,22,383,384,385,386,23,24,25,387,26,388,389,390,206,27,207,28,208,29,209,391,392,210,211,30,393,394,31,32,212,33,395,396,397,213,214,398,399,215,400,401,402,34,403,35,36,216,37,217,38,404,405,39,218,406,407,408,219,220,409,221,40,222,410,41,411,42,223,43,44,224,412,413,414,415,45,416,46,417,418,47,419,225,420,421,422,48,49,226,227,423,424,425,228,50,51,426,229,230,427,231,232,428,233,429,234,52,53,54,235,236,430,55,237,238,431,239,432,56,57,433,434,58,59,435,436,240,437,241,60,242,438,439,440,243,61,244,245,441,442,443,444,445,246,446,447,448,62,247,449,248,450,63,64,65,451,452,453,454,249,455,456,250,251,66,67,252,68,69,253,457,70,254,255,458,256,459,257,258,460,71,72,461,73,462,74,463,464,75,465,76,259,260,77,466,467,78,468,79,469,470,471,472,473,474,80,475,476,477,261,478,479,480,262,481,81,82,482,483,484,83,485,486,487,488,263,84,489,264,490,85,491,492,493,86,494,265,495,496,266,267,87,268,88,269,270,498,89,499,500,501,271,502,90,503,504,272,91,505,506,507,273,508,274,509,275,276,277,92,278,510,511,512,513,93,514,515,516,94,517,518,279,519,280,281,95,520,282,283,521,96,522,523,524,97,525,284,526,98,99,285,527,100,101,102,528,103,529,286,530,287,104,105,288,289,531,532,290,291,533,106,107,292,108,293,294,109,534,535,295,296,297,298,299,300,301,110,111,112,113,536,537,538,539,302,540,114,303,541,115,542,304,543,544,545,116,546,547,548,117,549,550,118,305,551,552,553,554,555,556,557,306,558,119,120,559,121,560,122,561,562,563,564,307,565,308,123,124,566,567,125,126,568,569,570,571,572,573,574,575,127,128,129,130,131,576,132,577,309,310,133,578,579,134,580,311,581,582,135,312,313,583,584,585,586,136,587,137,138,314,139,588,140,315,316,141,317,142,143,318,319,589,144,320,145,146,147,321,148,149,322,590,323,591,150,324,325,151,326,152,592,593,153,594,154,595,327,596,328,155,156,597,598,329,330,599,157,158,159,331,332,600,160,601,602,333,334,603,335,604,605,606,161,607,608,162,609,336,337,163,610,611,164,338,339,612,613,340,341,614,342,165,166,615,343,167,344,345,616,168,169,617,618,170,171,346,619,172,347,621,622,623,624,348,349,350,173,351,174,175,352,625,626,353,627,354,628,176,177,178,179,629,630,180,631,632,355,181,356,182,633,634,635,636,637,357,638,358,639,183,184,359,640,641,642,643,185]},"name":"game_111013301","importBase":"import","nativeBase":"native","debug":false,"isZip":false,"encrypted":false,"versions":{"import":["0d923bddd","848e9"],"native":[0,"2993c",1,"3f143",2,"5d372",3,"c63e4",4,"f7b07",5,"a6c18",6,"132c5",7,"2993c",8,"a0650",9,"634d0",10,"129f5",11,"90c1b",12,"d238a",13,"81a0c",14,"b6051",15,"9ba8e",16,"25f80",17,"957fc",18,"0bdb5",19,"85d8e",20,"3c8d0",21,"e7f21",22,"274bf",23,"73cb5",24,"8c2ff",25,"588f1",26,"095ff",27,"ed475",28,"3a74f",29,"f93db",30,"06068",31,"3feb3",32,"aff2a",33,"2993c",34,"58f9b",35,"d5d20",36,"2993c",37,"b13c5",38,"b8f63",39,"7b082",40,"a1210",41,"277e4",42,"e5495",43,"a0a3d",44,"50821",45,"a7bc6",46,"6d0a9",47,"ae9c9",48,"8d53c",49,"babfb",50,"d5bb2",51,"2993c",52,"ffb4e",53,"128ec",54,"65bce",55,"e4e28",56,"ebc89",57,"e01e9",58,"1e5d2",59,"74ea5",60,"2993c",61,"518bf",62,"a3e96",63,"12ce6",64,"7691f",65,"2993c",66,"74f3e",67,"8b63b",68,"ccd93",69,"11ef1",70,"b1591",71,"7847e",72,"586b3",73,"fe633",74,"2fd29",75,"4a9c6",76,"82cfc",77,"c4a73",78,"c92dd",79,"e44ef",80,"75123",81,"71670",82,"fe633",83,"22d67",84,"6dd47",85,"02275",86,"703ae",87,"84be7",88,"fa5cb",89,"7ce00",90,"2b57d",91,"869bb",92,"cfc71",93,"b8b5d",94,"206ef",95,"b127d",96,"fce0f",97,"2993c",98,"a28ec",99,"9fa48",100,"b3943",101,"97c31",102,"45484",103,"6f1b3",104,"7bee3",105,"99e5d",106,"bf215",107,"8f83d",108,"5f82f",109,"9cb06",110,"e3c7b",111,"2993c",112,"4efbc",113,"99cae",114,"e5586",115,"ae7b0",116,"4042b",117,"ae8db",118,"14728",119,"b03ca",120,"21fef",121,"c80c9",122,"2b2c2",123,"3a301",124,"1b879",125,"c2de6",126,"f1f6a",127,"dbf3e",128,"a0a3d",129,"0a9b1",130,"918a4",131,"73703",132,"60215",133,"5da79",134,"cea68",135,"c4d10",136,"a3f24",137,"4a9c6",138,"3e373",139,"4487f",140,"7580e",141,"15d2c",142,"b1aa5",143,"24bc4",144,"2acaf",145,"4d158",146,"ecd1e",147,"0174b",148,"8f937",149,"5113b",150,"34e43",151,"0b953",152,"95b93",153,"824f1",154,"bd794",155,"5b889",156,"1f1ad",157,"cd098",158,"8d90f",159,"f4bf2",160,"051bc",161,"c87db",162,"c19b0",163,"51c67",164,"a45cf",165,"61c86",166,"50342",167,"38326",168,"b3424",169,"9fe1a",170,"2993c",171,"17d19",172,"14735",173,"2993c",174,"1b045",175,"53130",176,"8c984",177,"64f2d",178,"5b935",179,"4cbeb",180,"96cc0",181,"10e08",182,"3bd97",183,"70a55",184,"c5ccb",185,"e5671"]}}